artifi/__init__.py
artifi/cloudflare/__init__.py
artifi/cloudflare/ext/__init__.py
artifi/cloudflare/ext/cfai.py
artifi/config/__init__.py
artifi/config/ext/__init__.py
artifi/config/ext/exception.py
artifi/config/ext/logger.py
artifi/discord/__init__.py
artifi/discord/cogs/__init__.py
artifi/discord/cogs/admin/__init__.py
artifi/discord/cogs/admin/authorize.py
artifi/discord/cogs/basic/__init__.py
artifi/discord/cogs/basic/network.py
artifi/discord/cogs/basic/ping.py
artifi/discord/cogs/basic/purge.py
artifi/discord/cogs/basic/shell.py
artifi/discord/cogs/basic/stats.py
artifi/discord/cogs/entertain/__init__.py
artifi/discord/cogs/entertain/music.py
artifi/discord/misc/__init__.py
artifi/discord/misc/discord_command.py
artifi/discord/misc/discord_func.py
artifi/discord/misc/discord_model.py
artifi/google/__init__.py
artifi/google/ext/__init__.py
artifi/google/ext/calender.py
artifi/google/ext/drive.py
artifi/google/ext/gmail.py
artifi/google/ext/people.py
artifi/google/ext/photos.py
artifi/google/ext/youtube.py
artifi/instagram/__init__.py
artifi/instagram/ext/__init__.py
artifi/utils/__init__.py
artifi/whatsapp/__init__.py
artifi/whatsapp/ext/__init__.py
artifi/whatsapp/ext/wam_model.py
Artifi-0.1.1.dist-info/LICENSE
Artifi-0.1.1.dist-info/METADATA
Artifi-0.1.1.dist-info/WHEEL
Artifi-0.1.1.dist-info/top_level.txt
Artifi-0.1.1.dist-info/RECORD
