Metadata-Version: 2.1
Name: Artifi
Version: 0.1.1
Summary: A Automation Tool Made By Noob
Home-page: https://github.com/Humanpredator/ArtiFi
Author: Humanpredator
Author-email: admin@reality.org.in
Classifier: Development Status :: 3 - Alpha
Classifier: Intended Audience :: Developers
Classifier: License :: OSI Approved :: GNU General Public License v3 (GPLv3)
Classifier: Programming Language :: Python :: 3.10
Requires-Python: >=3.10
License-File: LICENSE
Requires-Dist: aiohttp ==3.9.1
Requires-Dist: aiosignal ==1.3.1
Requires-Dist: APScheduler ==3.10.4
Requires-Dist: async-timeout ==4.0.3
Requires-Dist: attrs ==23.1.0
Requires-Dist: blinker ==1.7.0
Requires-Dist: cachetools ==5.3.2
Requires-Dist: certifi ==2023.11.17
Requires-Dist: cffi ==1.16.0
Requires-Dist: charset-normalizer ==3.3.2
Requires-Dist: click ==8.1.7
Requires-Dist: colorama ==0.4.6
Requires-Dist: discord ==2.3.2
Requires-Dist: discord.py ==2.3.2
Requires-Dist: Flask ==3.0.0
Requires-Dist: frozenlist ==1.4.1
Requires-Dist: google-api-core ==2.15.0
Requires-Dist: google-api-python-client ==2.111.0
Requires-Dist: google-auth ==2.25.2
Requires-Dist: google-auth-httplib2 ==0.2.0
Requires-Dist: google-auth-oauthlib ==1.2.0
Requires-Dist: googleapis-common-protos ==1.62.0
Requires-Dist: greenlet ==3.0.1
Requires-Dist: httplib2 ==0.22.0
Requires-Dist: idna ==3.6
Requires-Dist: instaloader ==4.10.2
Requires-Dist: itsdangerous ==2.1.2
Requires-Dist: Jinja2 ==3.1.2
Requires-Dist: MarkupSafe ==2.1.3
Requires-Dist: multidict ==6.0.4
Requires-Dist: oauthlib ==3.2.2
Requires-Dist: playwright ==1.40.0
Requires-Dist: protobuf ==4.25.1
Requires-Dist: psutil ==5.9.7
Requires-Dist: py-cpuinfo ==9.0.0
Requires-Dist: pyasn1 ==0.5.1
Requires-Dist: pyasn1-modules ==0.3.0
Requires-Dist: pycparser ==2.21
Requires-Dist: pyee ==11.0.1
Requires-Dist: PyNaCl ==1.5.0
Requires-Dist: pyparsing ==3.1.1
Requires-Dist: python-dotenv ==1.0.0
Requires-Dist: python-magic ==0.4.27
Requires-Dist: pytz ==2023.3.post1
Requires-Dist: requests ==2.31.0
Requires-Dist: requests-oauthlib ==1.3.1
Requires-Dist: rsa ==4.9
Requires-Dist: six ==1.16.0
Requires-Dist: speedtest-cli ==2.1.3
Requires-Dist: SQLAlchemy ==2.0.23
Requires-Dist: tenacity ==8.2.3
Requires-Dist: typing-extensions ==4.9.0
Requires-Dist: tzdata ==2023.3
Requires-Dist: tzlocal ==5.2
Requires-Dist: uritemplate ==4.1.1
Requires-Dist: urllib3 ==2.1.0
Requires-Dist: wavelink ==3.1.0
Requires-Dist: Werkzeug ==3.0.1
Requires-Dist: yarl ==1.9.2
